hohu/__init__.py
hohu/config.py
hohu/i18n.py
hohu/main.py
hohu/commands/__init__.py
hohu/commands/system.py
hohu/commands/admin/__init__.py
hohu/commands/admin/create.py
hohu/commands/admin/dev.py
hohu/commands/admin/init.py
hohu/locales/en.json
hohu/locales/zh.json
hohu/utils/project.py
hohu-0.1.3.dist-info/METADATA
hohu-0.1.3.dist-info/WHEEL
hohu-0.1.3.dist-info/entry_points.txt
hohu-0.1.3.dist-info/licenses/LICENSE
hohu-0.1.3.dist-info/RECORD
