Metadata-Version: 2.4
Name: hohu
Version: 0.1.3
Summary: A full-stack project management CLI tool for Hohu Admin ecosystem.
Project-URL: Homepage, https://github.com/aihohu/hohu-cli
Project-URL: Issues, https://github.com/aihohu/hohu-cli/issues
Author-email: hohu <hohu@hohu.org>
License: MIT License
License-File: LICENSE
Keywords: admin-system,ai,api,cli,fastapi,hohu,mcp,openapi,tools
Classifier: Development Status :: 4 - Beta
Classifier: Environment :: Console
Classifier: Intended Audience :: Developers
Classifier: License :: OSI Approved :: MIT License
Classifier: Operating System :: OS Independent
Classifier: Programming Language :: Python :: 3
Classifier: Topic :: Software Development :: Code Generators
Classifier: Topic :: Software Development :: Libraries :: Python Modules
Classifier: Topic :: Utilities
Requires-Python: >=3.10
Requires-Dist: gitpython>=3.1.46
Requires-Dist: questionary>=2.1.1
Requires-Dist: rich>=14.2.0
Requires-Dist: ruff>=0.14.10
Requires-Dist: typer>=0.21.0
